[
  {
    "full_name": "denoland/fresh",
    "stargazers_count": 9106,
    "open_issues_count": 139,
    "forks_count": 347
  },
  {
    "full_name": "withastro/astro",
    "stargazers_count": 20898,
    "open_issues_count": 88,
    "forks_count": 968
  },
  {
    "full_name": "FormidableLabs/urql",
    "stargazers_count": 7511,
    "open_issues_count": 32,
    "forks_count": 360
  },
  {
    "full_name": "vitejs/vite",
    "stargazers_count": 48132,
    "open_issues_count": 610,
    "forks_count": 4042
  },
  {
    "full_name": "vitejs/vite",
    "stargazers_count": 48132,
    "open_issues_count": 610,
    "forks_count": 4042
  },
  {
    "full_name": "preactjs/preact",
    "stargazers_count": 33071,
    "open_issues_count": 219,
    "forks_count": 1822
  }
]